build/lib/mdns_client/__init__.py
build/lib/mdns_client/client.py
build/lib/mdns_client/constants.py
build/lib/mdns_client/parser.py
build/lib/mdns_client/responder.py
build/lib/mdns_client/structs.py
build/lib/mdns_client/util.py
build/lib/mdns_client/service_discovery/__init__.py
build/lib/mdns_client/service_discovery/discovery.py
build/lib/mdns_client/service_discovery/service_monitor.py
build/lib/mdns_client/service_discovery/service_response.py
build/lib/mdns_client/service_discovery/txt_discovery.py
mdns_client/__init__.py
mdns_client/client.py
mdns_client/constants.py
mdns_client/parser.py
mdns_client/responder.py
mdns_client/structs.py
mdns_client/util.py
mdns_client/service_discovery/__init__.py
mdns_client/service_discovery/discovery.py
mdns_client/service_discovery/service_monitor.py
mdns_client/service_discovery/service_response.py
mdns_client/service_discovery/txt_discovery.py
micropython_mdns-1.5.2.dist-info/METADATA
micropython_mdns-1.5.2.dist-info/WHEEL
micropython_mdns-1.5.2.dist-info/top_level.txt
micropython_mdns-1.5.2.dist-info/zip-safe
micropython_mdns-1.5.2.dist-info/RECORD
