Metadata-Version: 2.1
Name: micropython-mdns
Version: 1.5.2
Summary: MDNS for micropython with service discovery support
Home-page: https://github.com/cbrand/micropython-mdns
Author: Christoph Brand
Author-email: ch.brand@gmail.com
License: MIT
Project-URL: GitHub, https://github.com/cbrand/micropython-mdns
Classifier: Development Status :: 5 - Production/Stable
Classifier: Intended Audience :: Developers
Classifier: Programming Language :: Python :: Implementation :: MicroPython
Classifier: Programming Language :: Python
Classifier: Programming Language :: Python :: 3
Classifier: Programming Language :: Python :: 3.8
Classifier: Programming Language :: Python :: 3.9
Classifier: Programming Language :: Python :: 3.10
Classifier: Programming Language :: Python :: 3.11
Classifier: Programming Language :: Python :: 3.12
Classifier: Programming Language :: Python :: 3.13
Classifier: Programming Language :: Python :: 3 :: Only
Classifier: Topic :: Software Development :: Libraries :: Python Modules
Classifier: Topic :: System :: Networking
Classifier: License :: OSI Approved :: MIT License
Requires-Python: >=3.8
